subxtpy-0.2.0.dist-info/METADATA
subxtpy-0.2.0.dist-info/WHEEL
subxtpy-0.2.0.dist-info/license_files/LICENSE.md
subxtpy/__init__.py
subxtpy/subxtpy.cpython-311-darwin.so
subxtpy-0.2.0.dist-info/RECORD
