Metadata-Version: 2.3
Name: subxtpy
Version: 0.2.0
License-File: LICENSE.md
Author-email: Philomath Ingeniare <philoniare@gmail.com>
License: Apache-2.0
